AUTHORS
CHANGES.txt
COPYING
README.txt
TODO.txt
setup.py
docs/RELEASE.howto
searchform/__init__.py
searchform/forms.py
searchform/jsi18n_urls.py
searchform/registry.py
searchform/terms.py
searchform/tests.py
searchform/urls.py
searchform/utils.py
searchform.egg-info/PKG-INFO
searchform.egg-info/SOURCES.txt
searchform.egg-info/dependency_links.txt
searchform.egg-info/not-zip-safe
searchform.egg-info/top_level.txt
searchform/locale/de/LC_MESSAGES/django.po
searchform/locale/de/LC_MESSAGES/djangojs.po
searchform/locale/en/LC_MESSAGES/django.po
searchform/locale/en/LC_MESSAGES/djangojs.mo
searchform/locale/en/LC_MESSAGES/djangojs.po
searchform/locale/es/LC_MESSAGES/django.mo
searchform/locale/es/LC_MESSAGES/django.po
searchform/locale/es/LC_MESSAGES/djangojs.mo
searchform/locale/es/LC_MESSAGES/djangojs.po
searchform/locale/fr/LC_MESSAGES/django.po
searchform/locale/fr/LC_MESSAGES/djangojs.mo
searchform/locale/fr/LC_MESSAGES/djangojs.po
searchform/locale/ja/LC_MESSAGES/django.po
searchform/locale/ja/LC_MESSAGES/djangojs.po
searchform/locale/zh/LC_MESSAGES/django.po
searchform/locale/zh/LC_MESSAGES/djangojs.po
searchform/media/css/searchform.css
searchform/media/img/buscar_boton.png
searchform/media/img/flecha_left.png
searchform/media/img/flecha_right.png
searchform/media/img/remove-icon.png
searchform/media/js/jquery.smartsearch.js
searchform/templates/base_search_term.html
searchform/templates/exclusive_options_search_term.html
searchform/templates/exclusive_select_search_term.html
searchform/templates/free_text_search_term.html
searchform/templates/hidden_search_term.html
searchform/templates/long_text_search_term.html
searchform/templates/media.html
searchform/templates/multiple_options_search_term.html
searchform/templates/searchform.html