Metadata-Version: 1.0
Name: searchform
Version: 0.1.1
Summary: An advanced search form application for Django
Home-page: https://tracpub.yaco.es/djangoapps/wiki/SearchForm
Author: Lorenzo Gil Sanchez
Author-email: lgs@yaco.es
License: LGPL 3
Keywords: search django
Platform: UNKNOWN
